cdk_construct1/__init__.py
cdk_construct1/batch_fargate_construct.py
cdk_construct1/iam_construct.py
cd_construct1-0.1.dist-info/LICENSE
cd_construct1-0.1.dist-info/METADATA
cd_construct1-0.1.dist-info/WHEEL
cd_construct1-0.1.dist-info/top_level.txt
cd_construct1-0.1.dist-info/RECORD
